service_client/__init__.py
service_client/factories.py
service_client/formatters.py
service_client/json.py
service_client/mocks.py
service_client/plugins.py
service_client/spec_loaders.py
service_client/utils.py
aio_service_client-0.7.2.dist-info/LICENSE
aio_service_client-0.7.2.dist-info/METADATA
aio_service_client-0.7.2.dist-info/WHEEL
aio_service_client-0.7.2.dist-info/top_level.txt
aio_service_client-0.7.2.dist-info/zip-safe
aio_service_client-0.7.2.dist-info/RECORD
