Metadata-Version: 2.1
Name: aio-service-client
Version: 0.7.2
Summary: Service Client Framework powered by Python asyncio.
Home-page: https://github.com/alfred82santa/aio-service-client
Author: alfred82santa
Author-email: alfred82santa@gmail.com
License: LGPLv3
Platform: UNKNOWN
Classifier: Intended Audience :: Developers
Classifier: Programming Language :: Python
Classifier: Programming Language :: Python :: 3.6
Classifier: Programming Language :: Python :: 3.7
Classifier: Programming Language :: Python :: 3.8
Classifier: Programming Language :: Python :: 3.9
Classifier: License :: OSI Approved :: GNU Lesser General Public License v3 (LGPLv3)
Classifier: Development Status :: 4 - Beta
Requires-Dist: dirty-loader (>=0.2.2)
Requires-Dist: aiohttp (>=3.7.4)
Requires-Dist: configure-fork
